vicar/_DEFINITIONS.py
vicar/_LABEL_GRAMMAR.py
vicar/__init__.py
vicar/_version.py
vicar/vicarimage.py
vicar/vicarlabel.py
rms_vicar-1.1.2.dist-info/LICENSE
rms_vicar-1.1.2.dist-info/METADATA
rms_vicar-1.1.2.dist-info/WHEEL
rms_vicar-1.1.2.dist-info/top_level.txt
rms_vicar-1.1.2.dist-info/RECORD
